pyblocks_data/__init__.py
pyblocks_data/app.py
pyblocks_data/cli.py
pyblocks_data/lego_blocks/__init__.py
pyblocks_data/lego_blocks/basic_stats.py
pyblocks_data/lego_blocks/chatbot_llm.py
pyblocks_data/lego_blocks/clustering.py
pyblocks_data/lego_blocks/comparar_bases.py
pyblocks_data/lego_blocks/conciliacion.py
pyblocks_data/lego_blocks/correlation_analysis.py
pyblocks_data/lego_blocks/deteccion_avanzada.py
pyblocks_data/lego_blocks/deteccion_avanzada_outliers _anomalias.py
pyblocks_data/lego_blocks/eda_sweetviz.py
pyblocks_data/lego_blocks/estadistica_inferencial.py
pyblocks_data/lego_blocks/evaluacion_modelos.py
pyblocks_data/lego_blocks/export_project.py
pyblocks_data/lego_blocks/feature_engineering.py
pyblocks_data/lego_blocks/load_data.py
pyblocks_data/lego_blocks/missing_values.py
pyblocks_data/lego_blocks/modeling.py
pyblocks_data/lego_blocks/modelo_comparador.py
pyblocks_data/lego_blocks/nlp_analysis.py
pyblocks_data/lego_blocks/outlier_detection.py
pyblocks_data/lego_blocks/pca_dimensionality.py
pyblocks_data/lego_blocks/project_summary.py
pyblocks_data/lego_blocks/pronostico.py
pyblocks_data/lego_blocks/series_temporales.py
pyblocks_data/lego_blocks/transformations.py
pyblocks_data/lego_blocks/variable_selector.py
pyblocks_data/lego_blocks/visualizations.py
pyblocks_data/utils/helpers.py
pyblocks_data-1.0.5.dist-info/licenses/LICENSE.md
pyblocks_data-1.0.5.dist-info/METADATA
pyblocks_data-1.0.5.dist-info/WHEEL
pyblocks_data-1.0.5.dist-info/entry_points.txt
pyblocks_data-1.0.5.dist-info/top_level.txt
pyblocks_data-1.0.5.dist-info/RECORD
