Metadata-Version: 2.4
Name: pyblocks_data
Version: 1.0.5
Summary: Interfaz visual para análisis de datos y Machine Learning en Streamlit
Author: Ana María Maraboli Pavez
Requires-Python: >=3.10
License-File: LICENSE.md
Requires-Dist: streamlit
Requires-Dist: pandas
Requires-Dist: numpy<2.1
Requires-Dist: scikit-learn
Requires-Dist: matplotlib
Requires-Dist: seaborn
Requires-Dist: prophet
Requires-Dist: statsmodels
Requires-Dist: sweetviz
Requires-Dist: nltk
Requires-Dist: sentence-transformers
Requires-Dist: plotly
Requires-Dist: joblib
Requires-Dist: scipy
Requires-Dist: wordcloud
Requires-Dist: openai
Dynamic: author
Dynamic: description
Dynamic: description-content-type
Dynamic: license-file
Dynamic: requires-dist
Dynamic: requires-python
Dynamic: summary
